pytorch_quantization/__init__.py
pytorch_quantization/quant_modules.py
pytorch_quantization/tensor_quant.py
pytorch_quantization/version.py
pytorch_quantization/calib/__init__.py
pytorch_quantization/calib/calibrator.py
pytorch_quantization/calib/histogram.py
pytorch_quantization/calib/max.py
pytorch_quantization/nn/__init__.py
pytorch_quantization/nn/functional.py
pytorch_quantization/nn/_functions/__init__.py
pytorch_quantization/nn/_functions/quant_rnn.py
pytorch_quantization/nn/modules/__init__.py
pytorch_quantization/nn/modules/_utils.py
pytorch_quantization/nn/modules/clip.py
pytorch_quantization/nn/modules/quant_conv.py
pytorch_quantization/nn/modules/quant_instancenorm.py
pytorch_quantization/nn/modules/quant_linear.py
pytorch_quantization/nn/modules/quant_pooling.py
pytorch_quantization/nn/modules/quant_rnn.py
pytorch_quantization/nn/modules/tensor_quantizer.py
pytorch_quantization/optim/__init__.py
pytorch_quantization/optim/helper.py
pytorch_quantization/utils/__init__.py
pytorch_quantization/utils/quant_logging.py
pytorch_quantization/utils/reduce_amax.py
pytorch_quantization-2.1.3.dist-info/LICENSE
pytorch_quantization-2.1.3.dist-info/METADATA
pytorch_quantization-2.1.3.dist-info/WHEEL
pytorch_quantization-2.1.3.dist-info/top_level.txt
pytorch_quantization-2.1.3.dist-info/RECORD
