Metadata-Version: 2.1
Name: pytorch-quantization
Version: 2.1.3
Summary: NVIDIA Pytorch quantization toolkit
Home-page: https://github.com/nvidia/tensorrt/tools/pytorch-quantization
Author: NVIDIA
Author-email: nvidia@nvidia.com
License: Apache 2.0
Platform: UNKNOWN
License-File: LICENSE
Requires-Dist: numpy
Requires-Dist: absl-py (>=0.7.0)
Requires-Dist: scipy
Requires-Dist: sphinx-glpi-theme
Requires-Dist: prettytable
Requires-Dist: pyyaml
